{"OutputFileHashSum":"6CD12C8F030F69A0C54B19518411262750BE6E181A6F9B4B954BEA8A930AFB97","Converted":true,"OutputModifyDate":"2024-05-13T09:23:59.3514527Z","Metadatas":[],"MetadataTypes":[{"CategoryName":"VuGen.Replay","MetadataTypeName":"HP.LR.Vugen.NotifyTransaction","Id":1},{"CategoryName":"VuGen.Replay","MetadataTypeName":"HP.LR.Vugen.Warning","Id":2},{"CategoryName":"VuGen.Replay","MetadataTypeName":"HP.LR.Vugen.NotifyAny","Id":3},{"CategoryName":"VuGen.Replay","MetadataTypeName":"HP.LR.Vugen.Iteration","Id":4}]}