{"OutputFileHashSum":"F13DE93E553C9794C4F4FBEDF03817DD225AD0D62A3C11B9429E1D59CD544CC4","Converted":true,"OutputModifyDate":"2024-02-22T10:46:56.7163909Z","Metadatas":[],"MetadataTypes":[{"CategoryName":"VuGen.Replay","MetadataTypeName":"HP.LR.Vugen.NotifyTransaction","Id":1},{"CategoryName":"VuGen.Replay","MetadataTypeName":"HP.LR.Vugen.Warning","Id":2},{"CategoryName":"VuGen.Replay","MetadataTypeName":"HP.LR.Vugen.Iteration","Id":3},{"CategoryName":"VuGen.Replay","MetadataTypeName":"Utt.Debugger.Warning","Id":4},{"CategoryName":"VuGen.Replay","MetadataTypeName":"HP.LR.Vugen.NotifyAny","Id":5},{"CategoryName":"VuGen.Replay","MetadataTypeName":"Utt.Debugger.Error","Id":6}]}